ols.py
overlap_save-1.1.2.dist-info/METADATA
overlap_save-1.1.2.dist-info/WHEEL
overlap_save-1.1.2.dist-info/top_level.txt
overlap_save-1.1.2.dist-info/zip-safe
overlap_save-1.1.2.dist-info/RECORD
