Metadata-Version: 2.1
Name: overlap-save
Version: 1.1.2
Summary: Overlap-save method for fast convolution, like Scipy's fftconvolve, but memory-efficient
Home-page: https://github.com/fasiha/overlap_save-py
Author: Ahmed Fasih
Author-email: ahmed@aldebrn.me
License: Unlicense
Keywords: overlap save add fast convolution convolve fft fftconvolve fir filter
Platform: UNKNOWN
Requires-Dist: array-range
Requires-Dist: nextprod
Requires-Dist: numpy
